mlable/__init__.py
mlable/blocks/__init__.py
mlable/blocks/attention/__init__.py
mlable/blocks/attention/generic.py
mlable/blocks/attention/transformer.py
mlable/blocks/convolution/__init__.py
mlable/blocks/convolution/generic.py
mlable/blocks/convolution/resnet.py
mlable/blocks/convolution/unet.py
mlable/blocks/normalization.py
mlable/blocks/shaping.py
mlable/caching.py
mlable/data.py
mlable/layers/__init__.py
mlable/layers/embedding.py
mlable/layers/shaping.py
mlable/layers/transformer.py
mlable/masking.py
mlable/maths/__init__.py
mlable/maths/ops.py
mlable/maths/probs.py
mlable/metrics.py
mlable/models/__init__.py
mlable/models/autoencoder.py
mlable/models/diffusion.py
mlable/models/generic.py
mlable/sampling.py
mlable/schedules.py
mlable/shapes.py
mlable/shaping/__init__.py
mlable/shaping/axes.py
mlable/shaping/hilbert.py
mlable/text.py
mlable/utils.py
mlable-0.22.10.dist-info/METADATA
mlable-0.22.10.dist-info/WHEEL
mlable-0.22.10.dist-info/RECORD
