Metadata-Version: 2.3
Name: mlable
Version: 0.22.10
Summary: Tensorflow libs: layers, metrics, ops, etc.
License: .github/LICENSE.md
Author: apehex
Author-email: apehex@protonmail.com
Requires-Python: >=3.10,<4.0
Classifier: License :: Other/Proprietary License
Classifier: Programming Language :: Python :: 3
Classifier: Programming Language :: Python :: 3.10
Classifier: Programming Language :: Python :: 3.11
Classifier: Programming Language :: Python :: 3.12
Classifier: Programming Language :: Python :: 3.13
Requires-Dist: densecurves (>=0.1)
Requires-Dist: tensorflow (>=2.16,<2.20)
